theory_ai/model.py
theory_ai-0.0.1.dist-info/LICENSE
theory_ai-0.0.1.dist-info/WHEEL
theory_ai-0.0.1.dist-info/METADATA
theory_ai-0.0.1.dist-info/RECORD
