Metadata-Version: 2.1
Name: theory-ai
Version: 0.0.1
Summary: Cloud native machine learning primitives
License: Apache 2.0
Author: Sole Ahab
Author-email: old.ocean.creature@gmail.com
Requires-Python: >=3.10,<4.0
Classifier: License :: Other/Proprietary License
Classifier: Programming Language :: Python :: 3
Classifier: Programming Language :: Python :: 3.10
Requires-Dist: simple-parsing (>=0.0.19,<0.0.20)
